tomako/__init__.py
tomako/loader.py
tomako/template.py
tomako/tests/__init__.py
tomako/tests/__main__.py
tomako/tests/mako_loader_test.py
tomako/tests/uimodule_test.py
tomako/tests/util.py
tomako/tests/templates/uimodule.html
tomako/tests/templates/utf8.html
tomako-0.1.0.post1.dist-info/DESCRIPTION.rst
tomako-0.1.0.post1.dist-info/METADATA
tomako-0.1.0.post1.dist-info/RECORD
tomako-0.1.0.post1.dist-info/WHEEL
tomako-0.1.0.post1.dist-info/metadata.json
tomako-0.1.0.post1.dist-info/top_level.txt
