Metadata-Version: 2.0
Name: tomako
Version: 0.1.0.post1
Summary: Tomako is the easiest way to use Mako as a template engine for Tornado
Home-page: https://github.com/rcmachado/tomako
Author: Rodrigo Machado
Author-email: rcmachado@gmail.com
License: MIT
Keywords: tomako,mako,tornado
Platform: UNKNOWN
Requires-Dist: Mako (>=0.7.2)
Requires-Dist: tornado (>=2.3)
